dhybridrpy/__init__.py
dhybridrpy/containers.py
dhybridrpy/data.py
dhybridrpy/dhybridrpy.py
dhybridrpy-1.5.dist-info/licenses/LICENSE
dhybridrpy-1.5.dist-info/METADATA
dhybridrpy-1.5.dist-info/WHEEL
dhybridrpy-1.5.dist-info/top_level.txt
dhybridrpy-1.5.dist-info/RECORD
