Metadata-Version: 2.4
Name: dhybridrpy
Version: 1.5
Summary: A Python package to easily read input + output data from dHybridR.
Project-URL: Homepage, https://github.com/bwostler/dhybridrpy
Requires-Python: >=3.8
License-File: LICENSE
Requires-Dist: h5py
Requires-Dist: matplotlib
Requires-Dist: numpy
Requires-Dist: ruff
Requires-Dist: h5py
Requires-Dist: f90nml
Requires-Dist: pre-commit
Requires-Dist: dask
Dynamic: license-file
